[{"direction":"null","ts":1605756381620,"touch_size":112.5,"pressure":0.75,"velocity_x":0.0,"velocity_y":0.0,"x":110.0,"y":272.0},{"direction":"right","ts":1605756381801,"touch_size":112.5,"pressure":0.85,"velocity_x":0.0,"velocity_y":0.0,"x":111.11798,"y":272.0},{"direction":"right","ts":1605756381828,"touch_size":112.5,"pressure":0.85,"velocity_x":4.9575515,"velocity_y":-0.015862057,"x":112.35263,"y":272.0},{"direction":"right","ts":1605756381847,"touch_size":112.5,"pressure":0.83750004,"velocity_x":9.110962,"velocity_y":-0.0020730228,"x":114.21481,"y":272.0},{"direction":"right","ts":1605756381870,"touch_size":112.5,"pressure":0.825,"velocity_x":12.840948,"velocity_y":6.452228E-4,"x":120.81211,"y":272.0},{"direction":"right","ts":1605756381889,"touch_size":112.5,"pressure":0.825,"velocity_x":24.194307,"velocity_y":-0.0023104255,"x":125.677376,"y":272.0},{"direction":"right","ts":1605756381910,"touch_size":112.5,"pressure":0.8,"velocity_x":30.159042,"velocity_y":-0.002250153,"x":132.4277,"y":272.0},{"direction":"right","ts":1605756381930,"touch_size":112.5,"pressure":0.7875,"velocity_x":39.702522,"velocity_y":3.3704052E-4,"x":140.53946,"y":272.0},{"direction":"right","ts":1605756381951,"touch_size":112.5,"pressure":0.7875,"velocity_x":50.898914,"velocity_y":8.1295957E-4,"x":164.11304,"y":272.927},{"direction":"right","ts":1605756381971,"touch_size":112.5,"pressure":0.7875,"velocity_x":79.03059,"velocity_y":2.8733509,"x":180.53502,"y":273.0},{"direction":"right","ts":1605756381994,"touch_size":112.5,"pressure":0.77500004,"velocity_x":100.10494,"velocity_y":3.0585454,"x":196.58737,"y":272.94562},{"direction":"right","ts":1605756382014,"touch_size":112.5,"pressure":0.7875,"velocity_x":113.86252,"velocity_y":1.049537,"x":213.16785,"y":272.13486},{"direction":"right","ts":1605756382036,"touch_size":112.5,"pressure":0.77500004,"velocity_x":117.027,"velocity_y":-2.5451717,"x":248.77411,"y":269.0308},{"direction":"right","ts":1605756382058,"touch_size":112.5,"pressure":0.77500004,"velocity_x":108.47594,"velocity_y":-11.811258,"x":267.27295,"y":266.59088},{"direction":"right","ts":1605756382079,"touch_size":112.5,"pressure":0.77500004,"velocity_x":112.185196,"velocity_y":-16.215576,"x":286.62283,"y":264.1579},{"direction":"right","ts":1605756382102,"touch_size":112.5,"pressure":0.77500004,"velocity_x":117.992294,"velocity_y":-18.609074,"x":321.7662,"y":260.02338},{"direction":"right","ts":1605756382124,"touch_size":112.5,"pressure":0.77500004,"velocity_x":109.68902,"velocity_y":-14.411774,"x":338.06097,"y":258.3939},{"direction":"right","ts":1605756382147,"touch_size":112.5,"pressure":0.77500004,"velocity_x":98.43489,"velocity_y":-10.021846,"x":353.9372,"y":257.1349},{"direction":"right","ts":1605756382169,"touch_size":112.5,"pressure":0.7625,"velocity_x":91.33356,"velocity_y":-7.858386,"x":379.356,"y":255.01028},{"direction":"right","ts":1605756382191,"touch_size":112.5,"pressure":0.77500004,"velocity_x":72.383675,"velocity_y":-4.506673,"x":389.93176,"y":254.5},{"direction":"right","ts":1605756382211,"touch_size":112.5,"pressure":0.7625,"velocity_x":59.793644,"velocity_y":-2.7028818,"x":400.0062,"y":254.5},{"direction":"right","ts":1605756382237,"touch_size":112.5,"pressure":0.7625,"velocity_x":50.35765,"velocity_y":0.07305506,"x":420.7279,"y":254.5},{"direction":"right","ts":1605756382256,"touch_size":90.0,"pressure":0.7625,"velocity_x":56.555534,"velocity_y":2.7444243,"x":430.61053,"y":254.5},{"direction":"right","ts":1605756382275,"touch_size":90.0,"pressure":0.7625,"velocity_x":59.522224,"velocity_y":1.4847225,"x":439.14734,"y":254.5},{"direction":"right","ts":1605756382298,"touch_size":90.0,"pressure":0.77500004,"velocity_x":55.76619,"velocity_y":0.6393839,"x":446.43283,"y":254.5},{"direction":"right","ts":1605756382317,"touch_size":90.0,"pressure":0.7625,"velocity_x":46.003914,"velocity_y":5.9193285E-4,"x":452.43402,"y":254.5},{"direction":"right","ts":1605756382336,"touch_size":90.0,"pressure":0.7625,"velocity_x":34.96722,"velocity_y":3.3290827E-4,"x":454.25,"y":254.5},{"direction":"right","ts":1605756382370,"touch_size":90.0,"pressure":0.7875,"velocity_x":32.251427,"velocity_y":4.2505405E-4,"x":459.45737,"y":254.5},{"direction":"right","ts":1605756382391,"touch_size":90.0,"pressure":0.8,"velocity_x":43.48924,"velocity_y":-7.6382665E-4,"x":465.5319,"y":254.58865},{"direction":"right","ts":1605756382413,"touch_size":90.0,"pressure":0.7875,"velocity_x":29.28775,"velocity_y":0.8620919,"x":469.60345,"y":255.40086},{"direction":"right","ts":1605756382436,"touch_size":90.0,"pressure":0.7875,"velocity_x":18.104824,"velocity_y":6.599707,"x":474.55133,"y":257.02567},{"direction":"right","ts":1605756382458,"touch_size":90.0,"pressure":0.8,"velocity_x":5.5359674,"velocity_y":6.7343254,"x":475.83917,"y":257.83917},{"direction":"down","ts":1605756382480,"touch_size":90.0,"pressure":0.8,"velocity_x":0.5197127,"velocity_y":6.685385,"x":476.65115,"y":258.8023},{"direction":"down","ts":1605756382502,"touch_size":90.0,"pressure":0.8,"velocity_x":-0.8729175,"velocity_y":5.730709,"x":478.27682,"y":262.33047},{"direction":"down","ts":1605756382528,"touch_size":90.0,"pressure":0.8,"velocity_x":0.6941453,"velocity_y":10.809572,"x":479.0896,"y":265.44797},{"direction":"down","ts":1605756382549,"touch_size":90.0,"pressure":0.7875,"velocity_x":3.384769,"velocity_y":17.012575,"x":479.90176,"y":269.91055},{"direction":"down","ts":1605756382570,"touch_size":90.0,"pressure":0.77500004,"velocity_x":4.860553,"velocity_y":25.82252,"x":480.5,"y":284.825},{"direction":"down","ts":1605756382593,"touch_size":90.0,"pressure":0.77500004,"velocity_x":1.5589385,"velocity_y":52.19845,"x":480.15933,"y":296.9506},{"direction":"down","ts":1605756382614,"touch_size":90.0,"pressure":0.77500004,"velocity_x":-1.1838686,"velocity_y":70.31528,"x":479.19382,"y":309.9496},{"direction":"down","ts":1605756382638,"touch_size":90.0,"pressure":0.77500004,"velocity_x":-5.89222,"velocity_y":89.05496,"x":475.16904,"y":336.70886},{"direction":"down","ts":1605756382658,"touch_size":90.0,"pressure":0.7875,"velocity_x":-15.122903,"velocity_y":93.86857,"x":472.72885,"y":351.03644},{"direction":"down","ts":1605756382681,"touch_size":90.0,"pressure":0.7875,"velocity_x":-18.408222,"velocity_y":88.44981,"x":470.7019,"y":364.38477},{"direction":"down","ts":1605756382703,"touch_size":90.0,"pressure":0.7625,"velocity_x":-17.402506,"velocity_y":85.75626,"x":466.91467,"y":391.51202},{"direction":"down","ts":1605756382725,"touch_size":90.0,"pressure":0.7625,"velocity_x":-10.522129,"velocity_y":80.25806,"x":463.6355,"y":408.6636},{"direction":"down","ts":1605756382745,"touch_size":90.0,"pressure":0.77500004,"velocity_x":-13.328059,"velocity_y":88.80113,"x":461.03632,"y":424.43658},{"direction":"down","ts":1605756382767,"touch_size":90.0,"pressure":0.7625,"velocity_x":-18.220972,"velocity_y":101.194664,"x":458.60022,"y":439.39874},{"direction":"down","ts":1605756382790,"touch_size":90.0,"pressure":0.7625,"velocity_x":-19.151274,"velocity_y":102.89245,"x":455.31787,"y":469.457},{"direction":"down","ts":1605756382811,"touch_size":90.0,"pressure":0.7625,"velocity_x":-7.9761057,"velocity_y":86.997055,"x":453.68698,"y":482.09775},{"direction":"down","ts":1605756382833,"touch_size":90.0,"pressure":0.7625,"velocity_x":-6.7221694,"velocity_y":80.62915,"x":452.7811,"y":491.90805},{"direction":"down","ts":1605756382854,"touch_size":90.0,"pressure":0.7625,"velocity_x":-5.714602,"velocity_y":66.2518,"x":451.5,"y":507.73447},{"direction":"down","ts":1605756382876,"touch_size":90.0,"pressure":0.7625,"velocity_x":-2.4217045,"velocity_y":34.46637,"x":451.5,"y":514.2409},{"direction":"down","ts":1605756382898,"touch_size":90.0,"pressure":0.7625,"velocity_x":0.764262,"velocity_y":28.715097,"x":451.5,"y":520.2558},{"direction":"down","ts":1605756382917,"touch_size":90.0,"pressure":0.7625,"velocity_x":2.0162907,"velocity_y":29.181875,"x":451.5,"y":525.9641},{"direction":"down","ts":1605756382943,"touch_size":90.0,"pressure":0.7625,"velocity_x":2.1724262,"velocity_y":28.833199,"x":451.0,"y":536.0213},{"direction":"down","ts":1605756382962,"touch_size":90.0,"pressure":0.7625,"velocity_x":-1.9015003,"velocity_y":28.27667,"x":451.0,"y":540.08527},{"direction":"down","ts":1605756382986,"touch_size":90.0,"pressure":0.7625,"velocity_x":-1.3048623,"velocity_y":23.824142,"x":451.0,"y":546.5283},{"direction":"down","ts":1605756383005,"touch_size":90.0,"pressure":0.77500004,"velocity_x":0.5845392,"velocity_y":15.6097765,"x":450.5,"y":548.81805},{"direction":"down","ts":1605756383028,"touch_size":90.0,"pressure":0.77500004,"velocity_x":-0.824403,"velocity_y":12.1176,"x":450.5,"y":550.4449},{"direction":"down","ts":1605756383047,"touch_size":90.0,"pressure":0.77500004,"velocity_x":-1.9585313,"velocity_y":8.1828785,"x":450.5,"y":552.0675},{"direction":"down","ts":1605756383069,"touch_size":90.0,"pressure":0.77500004,"velocity_x":-1.1269944,"velocity_y":5.546922,"x":450.5,"y":553.9018},{"direction":"down","ts":1605756383088,"touch_size":90.0,"pressure":0.77500004,"velocity_x":0.9773018,"velocity_y":3.4632595,"x":450.5,"y":554.716},{"direction":"down","ts":1605756383108,"touch_size":90.0,"pressure":0.77500004,"velocity_x":0.611256,"velocity_y":2.5514305,"x":450.5,"y":555.53516},{"direction":"down","ts":1605756383128,"touch_size":90.0,"pressure":0.77500004,"velocity_x":0.0017406553,"velocity_y":2.9363098,"x":450.5,"y":556.34753},{"direction":"down","ts":1605756383147,"touch_size":90.0,"pressure":0.77500004,"velocity_x":-0.0021538127,"velocity_y":3.5643554,"x":450.5,"y":556.75},{"direction":"left","ts":1605756383169,"touch_size":90.0,"pressure":0.77500004,"velocity_x":-0.0014925654,"velocity_y":4.327668,"x":449.22156,"y":557.27844},{"direction":"left","ts":1605756383188,"touch_size":90.0,"pressure":0.77500004,"velocity_x":-3.5986114,"velocity_y":-0.10419043,"x":447.80075,"y":557.5},{"direction":"left","ts":1605756383207,"touch_size":90.0,"pressure":0.7625,"velocity_x":-7.569925,"velocity_y":0.4511006,"x":445.78433,"y":558.0},{"direction":"left","ts":1605756383230,"touch_size":90.0,"pressure":0.7625,"velocity_x":-12.639663,"velocity_y":2.938811,"x":442.39465,"y":558.72107},{"direction":"left","ts":1605756383251,"touch_size":90.0,"pressure":0.7625,"velocity_x":-18.822731,"velocity_y":3.959481,"x":437.19608,"y":559.03375},{"direction":"left","ts":1605756383273,"touch_size":90.0,"pressure":0.75,"velocity_x":-30.999706,"velocity_y":2.7476213,"x":419.9239,"y":559.5},{"direction":"left","ts":1605756383295,"touch_size":90.0,"pressure":0.75,"velocity_x":-60.84492,"velocity_y":1.3409892,"x":409.339,"y":559.5},{"direction":"left","ts":1605756383315,"touch_size":90.0,"pressure":0.75,"velocity_x":-73.79558,"velocity_y":-0.5890971,"x":397.70215,"y":560.2865},{"direction":"left","ts":1605756383337,"touch_size":90.0,"pressure":0.75,"velocity_x":-79.74171,"velocity_y":0.6034365,"x":367.38617,"y":560.91016},{"direction":"left","ts":1605756383357,"touch_size":90.0,"pressure":0.7375,"velocity_x":-97.74421,"velocity_y":3.3698719,"x":348.859,"y":561.7235},{"direction":"left","ts":1605756383382,"touch_size":90.0,"pressure":0.75,"velocity_x":-114.27105,"velocity_y":4.112881,"x":329.66504,"y":562.5363},{"direction":"left","ts":1605756383402,"touch_size":90.0,"pressure":0.75,"velocity_x":-127.04597,"velocity_y":4.83895,"x":310.97992,"y":563.3487},{"direction":"left","ts":1605756383426,"touch_size":90.0,"pressure":0.75,"velocity_x":-128.88156,"velocity_y":5.718981,"x":277.53552,"y":564.9732},{"direction":"left","ts":1605756383446,"touch_size":90.0,"pressure":0.7625,"velocity_x":-101.00584,"velocity_y":4.8756843,"x":262.144,"y":565.7819},{"direction":"left","ts":1605756383471,"touch_size":90.0,"pressure":0.75,"velocity_x":-90.59769,"velocity_y":4.8625603,"x":235.53865,"y":567.0},{"direction":"left","ts":1605756383495,"touch_size":90.0,"pressure":0.7625,"velocity_x":-75.49779,"velocity_y":3.9239242,"x":221.8856,"y":567.1743},{"direction":"left","ts":1605756383518,"touch_size":90.0,"pressure":0.7625,"velocity_x":-69.61219,"velocity_y":1.4746008,"x":209.45021,"y":567.5},{"direction":"left","ts":1605756383538,"touch_size":90.0,"pressure":0.7625,"velocity_x":-70.212265,"velocity_y":0.48361984,"x":186.87192,"y":567.5},{"direction":"left","ts":1605756383559,"touch_size":90.0,"pressure":0.75,"velocity_x":-66.846794,"velocity_y":-0.7125232,"x":176.30022,"y":567.5},{"direction":"left","ts":1605756383581,"touch_size":90.0,"pressure":0.75,"velocity_x":-60.88191,"velocity_y":-0.5305936,"x":166.55417,"y":567.0},{"direction":"left","ts":1605756383600,"touch_size":90.0,"pressure":0.7625,"velocity_x":-53.71467,"velocity_y":-2.5109634,"x":156.81888,"y":566.90155},{"direction":"left","ts":1605756383622,"touch_size":90.0,"pressure":0.77500004,"velocity_x":-55.216774,"velocity_y":-1.9381399,"x":137.29541,"y":565.7746},{"direction":"left","ts":1605756383642,"touch_size":90.0,"pressure":0.7625,"velocity_x":-56.355858,"velocity_y":-3.749847,"x":128.10393,"y":564.9604},{"direction":"left","ts":1605756383663,"touch_size":90.0,"pressure":0.7625,"velocity_x":-56.458885,"velocity_y":-4.4715734,"x":120.322784,"y":564.147},{"direction":"left","ts":1605756383686,"touch_size":90.0,"pressure":0.7625,"velocity_x":-51.771297,"velocity_y":-5.411659,"x":108.63485,"y":562.52246},{"direction":"left","ts":1605756383706,"touch_size":90.0,"pressure":0.77500004,"velocity_x":-29.345959,"velocity_y":-5.7654324,"x":104.04518,"y":562.0},{"direction":"left","ts":1605756383729,"touch_size":90.0,"pressure":0.77500004,"velocity_x":-21.572533,"velocity_y":-4.986587,"x":100.08737,"y":561.39685},{"direction":"left","ts":1605756383749,"touch_size":90.0,"pressure":0.7875,"velocity_x":-18.114855,"velocity_y":-3.0590441,"x":96.84798,"y":560.587},{"direction":"left","ts":1605756383773,"touch_size":90.0,"pressure":0.8,"velocity_x":-15.955784,"velocity_y":-3.3211186,"x":92.422676,"y":559.5},{"direction":"left","ts":1605756383793,"touch_size":90.0,"pressure":0.8,"velocity_x":-9.408491,"velocity_y":-3.90429,"x":91.14591,"y":559.5},{"direction":"left","ts":1605756383813,"touch_size":90.0,"pressure":0.8,"velocity_x":-5.4604983,"velocity_y":-1.8553272,"x":90.33353,"y":558.83356},{"direction":"up","ts":1605756383836,"touch_size":90.0,"pressure":0.8,"velocity_x":-1.9493262,"velocity_y":-0.32912624,"x":88.70896,"y":557.209},{"direction":"up","ts":1605756383856,"touch_size":90.0,"pressure":0.7875,"velocity_x":-1.285289,"velocity_y":-5.2034025,"x":87.8962,"y":555.6886},{"direction":"up","ts":1605756383877,"touch_size":90.0,"pressure":0.77500004,"velocity_x":-3.38687,"velocity_y":-8.784995,"x":87.08404,"y":552.4202},{"direction":"up","ts":1605756383897,"touch_size":90.0,"pressure":0.77500004,"velocity_x":-4.866927,"velocity_y":-14.903518,"x":86.5,"y":547.38556},{"direction":"up","ts":1605756383919,"touch_size":90.0,"pressure":0.7625,"velocity_x":-4.4694953,"velocity_y":-26.89502,"x":86.5,"y":532.1042},{"direction":"up","ts":1605756383940,"touch_size":90.0,"pressure":0.7625,"velocity_x":0.6692,"velocity_y":-55.363636,"x":86.5,"y":522.8105},{"direction":"up","ts":1605756383960,"touch_size":90.0,"pressure":0.7625,"velocity_x":2.233371,"velocity_y":-64.17482,"x":86.98132,"y":511.28015},{"direction":"up","ts":1605756383980,"touch_size":90.0,"pressure":0.75,"velocity_x":2.802369,"velocity_y":-71.784966,"x":88.0849,"y":495.85855},{"direction":"up","ts":1605756384002,"touch_size":90.0,"pressure":0.7625,"velocity_x":5.0368457,"velocity_y":-87.65567,"x":89.81932,"y":476.73254},{"direction":"up","ts":1605756384024,"touch_size":90.0,"pressure":0.77500004,"velocity_x":9.970517,"velocity_y":-113.46448,"x":94.68344,"y":436.2603},{"direction":"up","ts":1605756384045,"touch_size":90.0,"pressure":0.77500004,"velocity_x":18.651585,"velocity_y":-144.64203,"x":96.58816,"y":418.1184},{"direction":"up","ts":1605756384066,"touch_size":90.0,"pressure":0.7625,"velocity_x":16.722883,"velocity_y":-128.97125,"x":98.215,"y":402.56503},{"direction":"up","ts":1605756384089,"touch_size":90.0,"pressure":0.77500004,"velocity_x":13.404588,"velocity_y":-109.525475,"x":100.958305,"y":374.85443},{"direction":"up","ts":1605756384110,"touch_size":90.0,"pressure":0.7625,"velocity_x":5.81046,"velocity_y":-70.47214,"x":102.592575,"y":360.1668},{"direction":"up","ts":1605756384137,"touch_size":90.0,"pressure":0.77500004,"velocity_x":6.643689,"velocity_y":-71.28641,"x":105.41891,"y":333.71634},{"direction":"up","ts":1605756384158,"touch_size":90.0,"pressure":0.77500004,"velocity_x":9.375848,"velocity_y":-80.80311,"x":106.23143,"y":322.26},{"direction":"up","ts":1605756384181,"touch_size":90.0,"pressure":0.7875,"velocity_x":6.9767394,"velocity_y":-72.58356,"x":107.08786,"y":311.4289},{"direction":"up","ts":1605756384202,"touch_size":90.0,"pressure":0.7875,"velocity_x":3.565459,"velocity_y":-61.53588,"x":108.35709,"y":300.8578},{"direction":"up","ts":1605756384230,"touch_size":90.0,"pressure":0.7875,"velocity_x":4.2081895,"velocity_y":-56.695972,"x":109.98064,"y":282.6936},{"direction":"up","ts":1605756384253,"touch_size":90.0,"pressure":0.7875,"velocity_x":5.7680078,"velocity_y":-51.669987,"x":111.0,"y":270.24472},{"direction":"up","ts":1605756384274,"touch_size":90.0,"pressure":0.8,"velocity_x":2.2947772,"velocity_y":-31.116888,"x":111.5,"y":265.90524},{"direction":"up","ts":1605756384295,"touch_size":90.0,"pressure":0.8,"velocity_x":2.0152242,"velocity_y":-21.773129,"x":111.5,"y":262.80127},{"direction":"up","ts":1605756384315,"touch_size":90.0,"pressure":0.8125,"velocity_x":0.17819723,"velocity_y":-14.799088,"x":111.5,"y":260.90915},{"direction":"up","ts":1605756384337,"touch_size":90.0,"pressure":0.7625,"velocity_x":-1.1685677,"velocity_y":-7.703428,"x":111.5,"y":258.82785},{"direction":"up","ts":1605756384349,"touch_size":90.0,"pressure":0.6375,"velocity_x":-0.83736163,"velocity_y":1.5378394,"x":111.5,"y":258.5}]
