[{"direction":"null","pressure":0.675,"ts":1605819376997,"touch_size":90.0,"velocity_x":0.0,"velocity_y":0.0,"x":104.5,"y":245.0},{"direction":"up","pressure":0.7,"ts":1605819377021,"touch_size":90.0,"velocity_x":0.0,"velocity_y":0.0,"x":104.5,"y":244.25},{"direction":"right","pressure":0.725,"ts":1605819377072,"touch_size":90.0,"velocity_x":8.868517E-4,"velocity_y":-4.9181128,"x":105.85563,"y":244.5},{"direction":"right","pressure":0.7375,"ts":1605819377091,"touch_size":67.5,"velocity_x":9.72168,"velocity_y":-7.3557143E-4,"x":109.45403,"y":244.5},{"direction":"right","pressure":0.725,"ts":1605819377112,"touch_size":67.5,"velocity_x":30.035599,"velocity_y":-0.0012372675,"x":116.14929,"y":245.0},{"direction":"right","pressure":0.725,"ts":1605819377131,"touch_size":67.5,"velocity_x":49.052,"velocity_y":3.9585333,"x":127.308334,"y":245.0},{"direction":"right","pressure":0.725,"ts":1605819377148,"touch_size":67.5,"velocity_x":74.56481,"velocity_y":2.0862222,"x":142.92851,"y":245.5},{"direction":"right","pressure":0.725,"ts":1605819377166,"touch_size":67.5,"velocity_x":102.349754,"velocity_y":2.6502597,"x":161.74553,"y":245.5},{"direction":"right","pressure":0.725,"ts":1605819377187,"touch_size":67.5,"velocity_x":126.603966,"velocity_y":1.910865,"x":183.47275,"y":245.5},{"direction":"right","pressure":0.725,"ts":1605819377206,"touch_size":67.5,"velocity_x":147.8556,"velocity_y":0.45035467,"x":232.65646,"y":244.57324},{"direction":"right","pressure":0.725,"ts":1605819377224,"touch_size":67.5,"velocity_x":165.73357,"velocity_y":-3.7077515,"x":257.22162,"y":244.0},{"direction":"right","pressure":0.725,"ts":1605819377243,"touch_size":67.5,"velocity_x":166.1221,"velocity_y":-5.473865,"x":279.3857,"y":244.0},{"direction":"right","pressure":0.71250004,"ts":1605819377261,"touch_size":67.5,"velocity_x":147.95358,"velocity_y":-3.3533208,"x":300.89053,"y":244.0},{"direction":"right","pressure":0.71250004,"ts":1605819377281,"touch_size":67.5,"velocity_x":129.41212,"velocity_y":-0.24719346,"x":320.2876,"y":244.0},{"direction":"right","pressure":0.725,"ts":1605819377299,"touch_size":67.5,"velocity_x":116.17978,"velocity_y":1.548569,"x":337.61404,"y":244.0},{"direction":"right","pressure":0.725,"ts":1605819377317,"touch_size":67.5,"velocity_x":101.59946,"velocity_y":1.4043771,"x":353.5323,"y":244.0},{"direction":"right","pressure":0.725,"ts":1605819377335,"touch_size":67.5,"velocity_x":91.062195,"velocity_y":0.5974183,"x":366.65656,"y":244.0},{"direction":"right","pressure":0.725,"ts":1605819377351,"touch_size":67.5,"velocity_x":76.326996,"velocity_y":-5.3372094E-4,"x":376.81195,"y":244.44266},{"direction":"right","pressure":0.725,"ts":1605819377369,"touch_size":67.5,"velocity_x":58.839657,"velocity_y":0.9727783,"x":384.52792,"y":245.2535},{"direction":"right","pressure":0.725,"ts":1605819377390,"touch_size":67.5,"velocity_x":41.173615,"velocity_y":3.7453775,"x":396.6399,"y":247.37712},{"direction":"right","pressure":0.725,"ts":1605819377408,"touch_size":67.5,"velocity_x":20.31173,"velocity_y":8.827089,"x":402.1338,"y":248.68896},{"direction":"right","pressure":0.725,"ts":1605819377430,"touch_size":67.5,"velocity_x":21.262945,"velocity_y":9.453458,"x":407.4984,"y":249.49977},{"direction":"right","pressure":0.725,"ts":1605819377449,"touch_size":67.5,"velocity_x":25.528795,"velocity_y":7.5198197,"x":413.18466,"y":250.81209},{"direction":"right","pressure":0.725,"ts":1605819377471,"touch_size":67.5,"velocity_x":29.32801,"velocity_y":7.2521377,"x":418.25543,"y":251.6259},{"direction":"right","pressure":0.71250004,"ts":1605819377489,"touch_size":67.5,"velocity_x":31.214209,"velocity_y":5.7367926,"x":427.7458,"y":253.24916},{"direction":"right","pressure":0.6875,"ts":1605819377508,"touch_size":67.5,"velocity_x":27.924034,"velocity_y":4.2145996,"x":431.80682,"y":254.06137},{"direction":"right","pressure":0.6875,"ts":1605819377527,"touch_size":67.5,"velocity_x":23.827812,"velocity_y":3.9733498,"x":434.98874,"y":254.8722},{"direction":"right","pressure":0.5625,"ts":1605819377540,"touch_size":67.5,"velocity_x":19.769585,"velocity_y":4.863371,"x":437.0,"y":255.5},{"direction":"null","pressure":0.675,"ts":1605819377859,"touch_size":90.0,"velocity_x":0.0,"velocity_y":0.0,"x":475.0,"y":262.5},{"direction":"down","pressure":0.6875,"ts":1605819377890,"touch_size":90.0,"velocity_x":0.0,"velocity_y":0.0,"x":474.25,"y":264.0},{"direction":"right","pressure":0.7,"ts":1605819377906,"touch_size":112.5,"velocity_x":-4.8511167,"velocity_y":9.69261,"x":474.5,"y":264.01505},{"direction":"down","pressure":0.71250004,"ts":1605819377928,"touch_size":112.5,"velocity_x":4.379641,"velocity_y":-5.6701775,"x":474.5,"y":266.0752},{"direction":"down","pressure":0.71250004,"ts":1605819377946,"touch_size":112.5,"velocity_x":2.2942152,"velocity_y":8.181991,"x":474.33084,"y":270.35333},{"direction":"down","pressure":0.7,"ts":1605819377966,"touch_size":90.0,"velocity_x":0.54809004,"velocity_y":23.401337,"x":474.0,"y":278.30075},{"direction":"down","pressure":0.7,"ts":1605819377987,"touch_size":90.0,"velocity_x":-1.1825219,"velocity_y":41.846336,"x":474.0,"y":289.40143},{"direction":"down","pressure":0.71250004,"ts":1605819378007,"touch_size":90.0,"velocity_x":-1.7998599,"velocity_y":66.83953,"x":474.4168,"y":316.086},{"direction":"down","pressure":0.7,"ts":1605819378027,"touch_size":90.0,"velocity_x":1.5027068,"velocity_y":100.17892,"x":474.5,"y":330.6113},{"direction":"down","pressure":0.7,"ts":1605819378047,"touch_size":90.0,"velocity_x":2.6097817,"velocity_y":101.86033,"x":474.45792,"y":345.29947},{"direction":"down","pressure":0.7,"ts":1605819378066,"touch_size":90.0,"velocity_x":1.0200193,"velocity_y":95.829926,"x":473.6471,"y":360.35226},{"direction":"down","pressure":0.7,"ts":1605819378087,"touch_size":90.0,"velocity_x":-1.905381,"velocity_y":95.53322,"x":472.18036,"y":374.87674},{"direction":"down","pressure":0.6875,"ts":1605819378107,"touch_size":90.0,"velocity_x":-7.653712,"velocity_y":91.758026,"x":468.1342,"y":405.48355},{"direction":"down","pressure":0.7,"ts":1605819378128,"touch_size":90.0,"velocity_x":-15.867768,"velocity_y":91.49008,"x":465.69702,"y":420.21695},{"direction":"down","pressure":0.6875,"ts":1605819378147,"touch_size":90.0,"velocity_x":-17.165573,"velocity_y":91.553505,"x":463.25732,"y":434.0419},{"direction":"down","pressure":0.675,"ts":1605819378168,"touch_size":90.0,"velocity_x":-16.781435,"velocity_y":87.581795,"x":460.82602,"y":447.59457},{"direction":"down","pressure":0.675,"ts":1605819378187,"touch_size":90.0,"velocity_x":-16.163992,"velocity_y":81.34507,"x":458.89124,"y":460.58008},{"direction":"down","pressure":0.6875,"ts":1605819378208,"touch_size":90.0,"velocity_x":-13.884514,"velocity_y":75.17558,"x":455.1758,"y":482.9452},{"direction":"down","pressure":0.6875,"ts":1605819378228,"touch_size":90.0,"velocity_x":-9.882891,"velocity_y":64.51469,"x":453.5538,"y":491.23105},{"direction":"down","pressure":0.6875,"ts":1605819378248,"touch_size":90.0,"velocity_x":-8.461416,"velocity_y":51.001747,"x":452.21375,"y":497.50378},{"direction":"down","pressure":0.6875,"ts":1605819378269,"touch_size":90.0,"velocity_x":-7.785988,"velocity_y":36.320625,"x":451.40347,"y":502.5791},{"direction":"down","pressure":0.6875,"ts":1605819378289,"touch_size":90.0,"velocity_x":-5.4692187,"velocity_y":22.669771,"x":450.59268,"y":507.03662},{"direction":"down","pressure":0.675,"ts":1605819378309,"touch_size":90.0,"velocity_x":-3.5845573,"velocity_y":17.456089,"x":448.96735,"y":516.196},{"direction":"down","pressure":0.6875,"ts":1605819378334,"touch_size":90.0,"velocity_x":-3.4806008,"velocity_y":21.823664,"x":448.15704,"y":520.71484},{"direction":"down","pressure":0.675,"ts":1605819378353,"touch_size":90.0,"velocity_x":-4.242416,"velocity_y":24.783907,"x":447.5,"y":524.6271},{"direction":"down","pressure":0.6,"ts":1605819378379,"touch_size":90.0,"velocity_x":-4.608483,"velocity_y":25.902761,"x":447.5,"y":529.0574},{"direction":"down","pressure":0.5125,"ts":1605819378392,"touch_size":90.0,"velocity_x":0.56579816,"velocity_y":11.444347,"x":447.5,"y":529.5},{"direction":"null","pressure":0.675,"ts":1605819378743,"touch_size":112.5,"velocity_x":0.0,"velocity_y":0.0,"x":446.0,"y":564.0},{"direction":"left","pressure":0.675,"ts":1605819378773,"touch_size":112.5,"velocity_x":0.0,"velocity_y":0.0,"x":443.11713,"y":564.0},{"direction":"left","pressure":0.675,"ts":1605819378790,"touch_size":112.5,"velocity_x":10.849876,"velocity_y":0.0010080873,"x":441.2641,"y":564.0},{"direction":"left","pressure":0.6875,"ts":1605819378807,"touch_size":112.5,"velocity_x":-7.454529,"velocity_y":-0.005573278,"x":433.73456,"y":563.11224},{"direction":"left","pressure":0.675,"ts":1605819378824,"touch_size":112.5,"velocity_x":-40.377274,"velocity_y":-4.7827373,"x":421.95822,"y":562.29724},{"direction":"left","pressure":0.675,"ts":1605819378843,"touch_size":112.5,"velocity_x":-72.91312,"velocity_y":-6.639364,"x":405.20547,"y":560.9719},{"direction":"left","pressure":0.675,"ts":1605819378863,"touch_size":112.5,"velocity_x":-104.28741,"velocity_y":-8.4927435,"x":383.542,"y":560.1739},{"direction":"left","pressure":0.675,"ts":1605819378883,"touch_size":112.5,"velocity_x":-140.22894,"velocity_y":-8.8343525,"x":359.39658,"y":559.5},{"direction":"left","pressure":0.675,"ts":1605819378903,"touch_size":112.5,"velocity_x":-166.60545,"velocity_y":-6.3680606,"x":334.15912,"y":559.5},{"direction":"left","pressure":0.6875,"ts":1605819378923,"touch_size":112.5,"velocity_x":-177.02057,"velocity_y":-2.1077797,"x":284.41632,"y":560.57184},{"direction":"left","pressure":0.7,"ts":1605819378941,"touch_size":112.5,"velocity_x":-161.55788,"velocity_y":6.0275264,"x":261.31693,"y":560.5},{"direction":"left","pressure":0.6875,"ts":1605819378961,"touch_size":112.5,"velocity_x":-144.14511,"velocity_y":5.303317,"x":239.57854,"y":560.5},{"direction":"left","pressure":0.6875,"ts":1605819378982,"touch_size":112.5,"velocity_x":-132.47318,"velocity_y":2.1224852,"x":220.79253,"y":560.5},{"direction":"left","pressure":0.7,"ts":1605819378999,"touch_size":112.5,"velocity_x":-114.02096,"velocity_y":-0.84805894,"x":203.27457,"y":560.5},{"direction":"left","pressure":0.7,"ts":1605819379017,"touch_size":112.5,"velocity_x":-101.39026,"velocity_y":-1.5601074,"x":187.60672,"y":560.5},{"direction":"left","pressure":0.6875,"ts":1605819379035,"touch_size":112.5,"velocity_x":-87.81154,"velocity_y":-0.5535454,"x":173.92384,"y":560.5},{"direction":"left","pressure":0.7,"ts":1605819379053,"touch_size":112.5,"velocity_x":-75.47516,"velocity_y":-0.004168966,"x":161.89926,"y":561.2572},{"direction":"left","pressure":0.7,"ts":1605819379072,"touch_size":112.5,"velocity_x":-66.23525,"velocity_y":1.9155931,"x":151.18341,"y":562.06805},{"direction":"left","pressure":0.71250004,"ts":1605819379092,"touch_size":112.5,"velocity_x":-57.258766,"velocity_y":5.1247463,"x":132.59782,"y":564.69025},{"direction":"left","pressure":0.7,"ts":1605819379111,"touch_size":112.5,"velocity_x":-46.551636,"velocity_y":10.234534,"x":124.7398,"y":565.52893},{"direction":"left","pressure":0.7,"ts":1605819379136,"touch_size":112.5,"velocity_x":-42.554237,"velocity_y":8.447007,"x":119.12761,"y":566.3389},{"direction":"left","pressure":0.7,"ts":1605819379156,"touch_size":112.5,"velocity_x":-33.835335,"velocity_y":6.3710785,"x":114.235275,"y":567.15295},{"direction":"left","pressure":0.7,"ts":1605819379178,"touch_size":112.5,"velocity_x":-24.819687,"velocity_y":4.034578,"x":107.669785,"y":568.5},{"direction":"left","pressure":0.6875,"ts":1605819379198,"touch_size":112.5,"velocity_x":-11.51715,"velocity_y":3.7839036,"x":105.822624,"y":568.5},{"direction":"left","pressure":0.6,"ts":1605819379219,"touch_size":90.0,"velocity_x":-7.622424,"velocity_y":1.5378293,"x":104.5,"y":568.5},{"direction":"null","pressure":0.65000004,"ts":1605819379442,"touch_size":67.5,"velocity_x":0.0,"velocity_y":0.0,"x":96.0,"y":593.5},{"direction":"left","pressure":0.6625,"ts":1605819379457,"touch_size":67.5,"velocity_x":0.0,"velocity_y":0.0,"x":95.416245,"y":594.08374},{"direction":"up","pressure":0.6625,"ts":1605819379524,"touch_size":67.5,"velocity_x":-4.8643274,"velocity_y":4.842736,"x":94.5,"y":592.0085},{"direction":"up","pressure":0.675,"ts":1605819379547,"touch_size":67.5,"velocity_x":1.8845768,"velocity_y":-18.665964,"x":94.0,"y":588.6208},{"direction":"up","pressure":0.675,"ts":1605819379568,"touch_size":90.0,"velocity_x":-2.9393904,"velocity_y":-26.492666,"x":94.0,"y":581.9102},{"direction":"up","pressure":0.6625,"ts":1605819379589,"touch_size":90.0,"velocity_x":0.02381302,"velocity_y":-45.81601,"x":94.76684,"y":571.23065},{"direction":"up","pressure":0.675,"ts":1605819379608,"touch_size":90.0,"velocity_x":4.416478,"velocity_y":-69.38815,"x":98.68234,"y":532.5707},{"direction":"up","pressure":0.675,"ts":1605819379628,"touch_size":90.0,"velocity_x":15.253966,"velocity_y":-138.74696,"x":101.824554,"y":506.78513},{"direction":"up","pressure":0.675,"ts":1605819379647,"touch_size":90.0,"velocity_x":21.211338,"velocity_y":-172.78441,"x":105.057045,"y":477.8915},{"direction":"up","pressure":0.675,"ts":1605819379668,"touch_size":90.0,"velocity_x":24.079762,"velocity_y":-196.3201,"x":107.494576,"y":452.55423},{"direction":"up","pressure":0.675,"ts":1605819379688,"touch_size":90.0,"velocity_x":22.491144,"velocity_y":-196.73703,"x":109.786,"y":428.63898},{"direction":"up","pressure":0.6875,"ts":1605819379708,"touch_size":90.0,"velocity_x":16.639992,"velocity_y":-167.96265,"x":112.266846,"y":389.6293},{"direction":"up","pressure":0.6875,"ts":1605819379727,"touch_size":90.0,"velocity_x":5.0628777,"velocity_y":-107.10176,"x":113.07882,"y":371.76593},{"direction":"up","pressure":0.6875,"ts":1605819379746,"touch_size":90.0,"velocity_x":1.9911855,"velocity_y":-91.992325,"x":114.785065,"y":355.14935},{"direction":"up","pressure":0.7,"ts":1605819379767,"touch_size":90.0,"velocity_x":3.7855883,"velocity_y":-88.10674,"x":116.20331,"y":340.0437},{"direction":"up","pressure":0.7,"ts":1605819379788,"touch_size":90.0,"velocity_x":7.5319686,"velocity_y":-85.20304,"x":117.03002,"y":326.78986},{"direction":"up","pressure":0.71250004,"ts":1605819379808,"touch_size":90.0,"velocity_x":8.001337,"velocity_y":-78.967926,"x":119.13776,"y":306.98468},{"direction":"up","pressure":0.71250004,"ts":1605819379828,"touch_size":90.0,"velocity_x":5.005814,"velocity_y":-48.78511,"x":119.95106,"y":298.98944},{"direction":"up","pressure":0.71250004,"ts":1605819379848,"touch_size":90.0,"velocity_x":4.20811,"velocity_y":-37.55616,"x":120.76385,"y":291.88922},{"direction":"up","pressure":0.725,"ts":1605819379869,"touch_size":90.0,"velocity_x":4.283882,"velocity_y":-32.776386,"x":121.57505,"y":285.47464},{"direction":"up","pressure":0.725,"ts":1605819379890,"touch_size":90.0,"velocity_x":4.101275,"velocity_y":-32.109257,"x":122.38628,"y":279.79608},{"direction":"up","pressure":0.7375,"ts":1605819379911,"touch_size":90.0,"velocity_x":4.865272,"velocity_y":-30.482227,"x":123.5,"y":271.95325},{"direction":"up","pressure":0.725,"ts":1605819379937,"touch_size":90.0,"velocity_x":3.374722,"velocity_y":-18.596563,"x":123.5,"y":269.8547},{"direction":"up","pressure":0.725,"ts":1605819379957,"touch_size":90.0,"velocity_x":1.0733889,"velocity_y":-11.480533,"x":123.5,"y":268.3634},{"direction":"up","pressure":0.625,"ts":1605819379975,"touch_size":90.0,"velocity_x":-1.4560449,"velocity_y":-4.209596,"x":123.5,"y":266.75653}]
